any_document_extractor-0.1.3.dist-info/licenses/LICENSE
anydocumentextractor/__init__.py
any_document_extractor-0.1.3.dist-info/METADATA
any_document_extractor-0.1.3.dist-info/WHEEL
any_document_extractor-0.1.3.dist-info/top_level.txt
any_document_extractor-0.1.3.dist-info/RECORD
