Metadata-Version: 2.4
Name: any-document-extractor
Version: 0.1.3
Summary: A Python library for extracting text content from any document format.
Home-page: https://github.com/yeqing215777/any-document-extractor
Author: yeqing
Author-email: 215777@qq.com
Requires-Python: >=3.9
License-File: LICENSE
Requires-Dist: python-docx
Requires-Dist: python-multipart
Requires-Dist: openpyxl
Requires-Dist: pdfminer.six
Requires-Dist: camelot-py
Requires-Dist: python-pptx
Dynamic: author
Dynamic: author-email
Dynamic: description
Dynamic: description-content-type
Dynamic: home-page
Dynamic: license-file
Dynamic: requires-dist
Dynamic: requires-python
Dynamic: summary
